ccre_card_unique_id_exporter/__init__.py
ccre_card_unique_id_exporter/module.py
ccre_card_unique_id_exporter/parse.py
ccre_card_unique_id_exporter-0.0.3.dist-info/licenses/LICENSE
ccre_card_unique_id_exporter-0.0.3.dist-info/METADATA
ccre_card_unique_id_exporter-0.0.3.dist-info/WHEEL
ccre_card_unique_id_exporter-0.0.3.dist-info/top_level.txt
ccre_card_unique_id_exporter-0.0.3.dist-info/RECORD
