Metadata-Version: 2.4
Name: CCRE_Card_Unique_ID_Exporter
Version: 0.0.3
Summary: A simple Card Unique ID Exporter
Home-page: https://github.com/taxi-tabby/CCRE_Card_Unique_ID_Exporter
Author: taxi-tabby
Author-email: taxi_tabby <rkdmf0000@gmail.com>
Maintainer-email: taxi_tabby <rkdmf0000@gmail.com>
License-Expression: MIT
Project-URL: Homepage, https://github.com/taxi-tabby/CCRE_Card_Unique_ID_Exporter
Keywords: APDU,Smart Card,IC Card,USIM,Credit Card or something else
Classifier: Development Status :: 3 - Alpha
Classifier: Intended Audience :: Developers
Classifier: Topic :: Software Development :: Libraries :: Python Modules
Classifier: Programming Language :: Python :: 3
Requires-Python: >=3.9
License-File: LICENSE
Requires-Dist: pyscard==2.2.1
Provides-Extra: dev
Requires-Dist: check-manifest; extra == "dev"
Dynamic: author
Dynamic: home-page
Dynamic: license-file
